{
	"name": "Table_HumanResources_Department",
	"properties": {
		"linkedServiceName": {
			"referenceName": "LS_adventureworks_2022",
			"type": "LinkedServiceReference"
		},
		"annotations": [],
		"type": "SqlServerTable",
		"schema": [
			{
				"name": "DepartmentID",
				"type": "smallint",
				"precision": 5
			},
			{
				"name": "Name",
				"type": "nvarchar"
			},
			{
				"name": "GroupName",
				"type": "nvarchar"
			},
			{
				"name": "ModifiedDate",
				"type": "datetime",
				"precision": 23,
				"scale": 3
			}
		],
		"typeProperties": {
			"schema": "HumanResources",
			"table": "Department"
		}
	}
}